README.md
setup.py
pgabc/__init__.py
pgabc/auth.py
pgabc/indicator.py
pgabc/setup.py
pgabc/tushare_db_get.py
pgabc.egg-info/PKG-INFO
pgabc.egg-info/SOURCES.txt
pgabc.egg-info/dependency_links.txt
pgabc.egg-info/top_level.txt