Metadata-Version: 1.0
Name: pgabc
Version: 1.12.1
Summary: Data calulation
Home-page: https://github.com/HewayPg
Author: WangMin
Author-email: pgabc@sina.com
License: MIT License
Keywords: indicator
Platform: UNKNOWN
